livekit/plugins/turn_detector/__init__.py
livekit/plugins/turn_detector/base.py
livekit/plugins/turn_detector/english.py
livekit/plugins/turn_detector/external.py
livekit/plugins/turn_detector/log.py
livekit/plugins/turn_detector/models.py
livekit/plugins/turn_detector/multilingual.py
livekit/plugins/turn_detector/py.typed
livekit/plugins/turn_detector/version.py
livekit_plugins_external_turn_detector-1.2.15.dist-info/METADATA
livekit_plugins_external_turn_detector-1.2.15.dist-info/WHEEL
livekit_plugins_external_turn_detector-1.2.15.dist-info/RECORD
