Metadata-Version: 2.4
Name: livekit-plugins-external-turn-detector
Version: 1.2.15
Summary: End of utterance detection for LiveKit Agents
Project-URL: Documentation, https://docs.livekit.io
Project-URL: Website, https://livekit.io/
Project-URL: Source, https://github.com/livekit/agents
Author-email: Sam Dang <dangvansam98@gmail.com>
License-Expression: Apache-2.0
Keywords: audio,livekit,realtime,video,webrtc
Classifier: Intended Audience :: Developers
Classifier: License :: OSI Approved :: Apache Software License
Classifier: Programming Language :: Python :: 3
Classifier: Programming Language :: Python :: 3 :: Only
Classifier: Programming Language :: Python :: 3.9
Classifier: Programming Language :: Python :: 3.10
Classifier: Topic :: Multimedia :: Sound/Audio
Classifier: Topic :: Multimedia :: Video
Classifier: Topic :: Scientific/Engineering :: Artificial Intelligence
Requires-Python: >=3.9.0
Requires-Dist: jinja2
Requires-Dist: livekit-agents>=1.2.8
Requires-Dist: numpy>=1.26
Requires-Dist: onnxruntime>=1.18
Requires-Dist: openai>=1.0.0
Requires-Dist: transformers>=4.47.1
Requires-Dist: tritonclient[grpc]>=2.60.0
